rhodium/__init__.py
rhodium/_circular.py
rhodium/_exceptions.py
rhodium/_validation.py
rhodium/bbox.py
rhodium/bearing.py
rhodium/lat.py
rhodium/lng.py
rhodium/py.typed
elemental_rhodium-0.9.0.dist-info/METADATA
elemental_rhodium-0.9.0.dist-info/WHEEL
elemental_rhodium-0.9.0.dist-info/licenses/LICENSE
elemental_rhodium-0.9.0.dist-info/RECORD
