Metadata-Version: 2.4
Name: elemental-rhodium
Version: 0.9.0
Summary: Circular arithmetic for geographic coordinates — bearings, longitudes, and bounding boxes
Project-URL: Homepage, https://github.com/marszdf/rhodium
Project-URL: Documentation, https://github.com/marszdf/rhodium
Project-URL: Repository, https://github.com/marszdf/rhodium
Project-URL: Bug Tracker, https://github.com/marszdf/rhodium/issues
Project-URL: Issues, https://github.com/marszdf/rhodium/issues
Author-email: Marco Zaccaria Di Fraia <marco.z.difraia@gmail.com>
License-Expression: MIT
License-File: LICENSE
Keywords: antimeridian,arithmetic,aviation,bbox,bearing,circular,coordinates,geo,geospatial,gis,latitude,longitude,maritime,navigation
Classifier: Development Status :: 4 - Beta
Classifier: Intended Audience :: Developers
Classifier: Intended Audience :: Science/Research
Classifier: License :: OSI Approved :: MIT License
Classifier: Operating System :: OS Independent
Classifier: Programming Language :: Python :: 3
Classifier: Programming Language :: Python :: 3.9
Classifier: Programming Language :: Python :: 3.10
Classifier: Programming Language :: Python :: 3.11
Classifier: Programming Language :: Python :: 3.12
Classifier: Programming Language :: Python :: 3.13
Classifier: Topic :: Scientific/Engineering
Classifier: Topic :: Scientific/Engineering :: GIS
Classifier: Topic :: Software Development :: Libraries
Classifier: Topic :: Software Development :: Libraries :: Python Modules
Classifier: Typing :: Typed
Requires-Python: >=3.9
Provides-Extra: test
Requires-Dist: hypothesis>=6.0; extra == 'test'
Requires-Dist: pytest-cov>=4.0; extra == 'test'
Requires-Dist: pytest>=7.0; extra == 'test'
